Workbook

Sheet Indice
A1: Fenómeno | B1: Observatorio | C1: Código | D1: PDF | E1: JSON | F1: CSV | G1: Excel | H1: Imagen | I1: Texto | J1: PBF (Mapas) | K1: Total datos
A2: F1 — IA y Capacidades Estratégicas | B2: AI_Index_Stanford | C2: AIINDEX | D2: 44 | E2: 0 | F2: 17 | G2: 4 | H2: 0 | I2: 0 | J2: 0 | K2: =SUM(D2:J2) -> 65
A3: F1 — IA y Capacidades Estratégicas | B3: Atlantic_Council | C3: ATLCOUNCIL | D3: 0 | E3: 186 | F3: 0 | G3: 0 | H3: 0 | I3: 0 | J3: 0 | K3: =SUM(D3:J3) -> 186
A4: F1 — IA y Capacidades Estratégicas | B4: CENIA | C4: CENIA | D4: 12 | E4: 15 | F4: 0 | G4: 0 | H4: 0 | I4: 0 | J4: 0 | K4: =SUM(D4:J4) -> 27
A5: F1 — IA y Capacidades Estratégicas | B5: CSET_Georgetown | C5: CSET | D5: 127 | E5: 0 | F5: 0 | G5: 0 | H5: 0 | I5: 0 | J5: 0 | K5: =SUM(D5:J5) -> 127
A6: F1 — IA y Capacidades Estratégicas | B6: DAIO | C6: DAIO | D6: 33 | E6: 1 | F6: 1 | G6: 0 | H6: 0 | I6: 0 | J6: 0 | K6: =SUM(D6:J6) -> 35
A7: F1 — IA y Capacidades Estratégicas | B7: Defensa21_LatAm | C7: DEFENSA21 | D7: 0 | E7: 2 | F7: 0 | G7: 0 | H7: 0 | I7: 0 | J7: 0 | K7: =SUM(D7:J7) -> 2
A8: F1 — IA y Capacidades Estratégicas | B8: ILIA_Latam | C8: ILIA | D8: 10 | E8: 0 | F8: 0 | G8: 0 | H8: 0 | I8: 0 | J8: 0 | K8: =SUM(D8:J8) -> 10
A9: F1 — IA y Capacidades Estratégicas | B9: RutaN_GEIAL | C9: RUTAN | D9: 5 | E9: 1 | F9: 1 | G9: 0 | H9: 0 | I9: 0 | J9: 0 | K9: =SUM(D9:J9) -> 7
A10: F2 — Seguridad del Entorno Espacial | B10: CSIS_Aerospace | C10: CSIS | D10: 110 | E10: 103 | F10: 1 | G10: 0 | H10: 0 | I10: 0 | J10: 0 | K10: =SUM(D10:J10) -> 214
A11: F2 — Seguridad del Entorno Espacial | B11: ESA_Space_Debris | C11: ESA | D11: 24 | E11: 16 | F11: 0 | G11: 0 | H11: 0 | I11: 0 | J11: 0 | K11: =SUM(D11:J11) -> 40
A12: F2 — Seguridad del Entorno Espacial | B12: INPE | C12: INPE | D12: 4 | E12: 55 | F12: 0 | G12: 0 | H12: 0 | I12: 0 | J12: 0 | K12: =SUM(D12:J12) -> 59
A13: F2 — Seguridad del Entorno Espacial | B13: SWF_Counterspace | C13: SWF | D13: 68 | E13: 56 | F13: 1 | G13: 0 | H13: 8 | I13: 1 | J13: 1 | K13: =SUM(D13:J13) -> 135
... A22: F3 — Dinámicas Territoriales | B22: Wilson_Center | C22: WILSON | D22: 0 | E22: 0 | F22: 0 | G22: 0 | H22: 0 | I22: 0 | J22: 0 | K22: =SUM(D22:J22) -> 0
A23: TOTAL | D23: =SUM(D2:D22) -> 759 | E23: =SUM(E2:E22) -> 954 | F23: =SUM(F2:F22) -> 26 | G23: =SUM(G2:G22) -> 4 | H23: =SUM(H2:H22) -> 8 | I23: =SUM(I2:I22) -> 1 | J23: =SUM(J2:J22) -> 74 | K23: =SUM(K2:K22) -> 1826

Sheet Resumen por Fenomeno
A1: Fenómeno | B1: Observatorios | C1: Total datos | D1: PDFs | E1: JSONs
A2: F1 — IA y Capacidades Estratégicas | B2: 8 | C2: 459 | D2: 231 | E2: 205
A3: F2 — Seguridad del Entorno Espacial | B3: 5 | C3: 479 | D3: 237 | E3: 230
A4: F3 — Dinámicas Territoriales | B4: 8 | C4: 888 | D4: 291 | E4: 519
A5: TOTAL | B5: =SUM(B2:B4) -> 21 | C5: =SUM(C2:C4) -> 1826 | D5: =SUM(D2:D4) -> 759 | E5: =SUM(E2:E4) -> 954

Sheet Inventario de Archivos
A1: Fenómeno | B1: Observatorio | C1: Código Observatorio | D1: DOC_ID | E1: Nombre estandarizado | F1: Carpeta | G1: Tipo
A2: F1 | B2: AI_Index_Stanford | C2: =VLOOKUP(B2,Indice!$B$1:$C$22,2,0) -> AIINDEX | D2: =$A2&"-"&$C2&"-"&TEXT(COUNTIFS($A$2:$A2,$A2,$C$2:$C2,$C2),"000") -> F1-AIINDEX-001 | E2: AIINDEX_ai-index-2024-ch1-research-development.pdf | F2: F1_IA_y_Capacidades_Estrategicas/AI_Index_Stanford/recursos/AI_Index_Report/pdfs | G2: PDF
A3: F1 | B3: AI_Index_Stanford | C3: =VLOOKUP(B3,Indice!$B$1:$C$22,2,0) -> AIINDEX | D3: =$A3&"-"&$C3&"-"&TEXT(COUNTIFS($A$2:$A3,$A3,$C$2:$C3,$C3),"000") -> F1-AIINDEX-002 | E3: AIINDEX_ai-index-2024-ch2-technical-performance.pdf | F3: F1_IA_y_Capacidades_Estrategicas/AI_Index_Stanford/recursos/AI_Index_Report/pdfs | G3: PDF
A4: F1 | B4: AI_Index_Stanford | C4: =VLOOKUP(B4,Indice!$B$1:$C$22,2,0) -> AIINDEX | D4: =$A4&"-"&$C4&"-"&TEXT(COUNTIFS($A$2:$A4,$A4,$C$2:$C4,$C4),"000") -> F1-AIINDEX-003 | E4: AIINDEX_ai-index-2024-ch3-responsible-ai.pdf | F4: F1_IA_y_Capacidades_Estrategicas/AI_Index_Stanford/recursos/AI_Index_Report/pdfs | G4: PDF
A5: F1 | B5: AI_Index_Stanford | C5: =VLOOKUP(B5,Indice!$B$1:$C$22,2,0) -> AIINDEX | D5: =$A5&"-"&$C5&"-"&TEXT(COUNTIFS($A$2:$A5,$A5,$C$2:$C5,$C5),"000") -> F1-AIINDEX-004 | E5: AIINDEX_ai-index-2024-ch4-economy.pdf | F5: F1_IA_y_Capacidades_Estrategicas/AI_Index_Stanford/recursos/AI_Index_Report/pdfs | G5: PDF
A6: F1 | B6: AI_Index_Stanford | C6: =VLOOKUP(B6,Indice!$B$1:$C$22,2,0) -> AIINDEX | D6: =$A6&"-"&$C6&"-"&TEXT(COUNTIFS($A$2:$A6,$A6,$C$2:$C6,$C6),"000") -> F1-AIINDEX-005 | E6: AIINDEX_ai-index-2024-ch5-science-medicine.pdf | F6: F1_IA_y_Capacidades_Estrategicas/AI_Index_Stanford/recursos/AI_Index_Report/pdfs | G6: PDF
A7: F1 | B7: AI_Index_Stanford | C7: =VLOOKUP(B7,Indice!$B$1:$C$22,2,0) -> AIINDEX | D7: =$A7&"-"&$C7&"-"&TEXT(COUNTIFS($A$2:$A7,$A7,$C$2:$C7,$C7),"000") -> F1-AIINDEX-006 | E7: AIINDEX_ai-index-2024-ch6-education.pdf | F7: F1_IA_y_Capacidades_Estrategicas/AI_Index_Stanford/recursos/AI_Index_Report/pdfs | G7: PDF
A8: F1 | B8: AI_Index_Stanford | C8: =VLOOKUP(B8,Indice!$B$1:$C$22,2,0) -> AIINDEX | D8: =$A8&"-"&$C8&"-"&TEXT(COUNTIFS($A$2:$A8,$A8,$C$2:$C8,$C8),"000") -> F1-AIINDEX-007 | E8: AIINDEX_ai-index-2025-ch1-research-development.pdf | F8: F1_IA_y_Capacidades_Estrategicas/AI_Index_Stanford/recursos/AI_Index_Report/pdfs | G8: PDF
A9: F1 | B9: AI_Index_Stanford | C9: =VLOOKUP(B9,Indice!$B$1:$C$22,2,0) -> AIINDEX | D9: =$A9&"-"&$C9&"-"&TEXT(COUNTIFS($A$2:$A9,$A9,$C$2:$C9,$C9),"000") -> F1-AIINDEX-008 | E9: AIINDEX_ai-index-2025-ch2-technical-performance.pdf | F9: F1_IA_y_Capacidades_Estrategicas/AI_Index_Stanford/recursos/AI_Index_Report/pdfs | G9: PDF
A10: F1 | B10: AI_Index_Stanford | C10: =VLOOKUP(B10,Indice!$B$1:$C$22,2,0) -> AIINDEX | D10: =$A10&"-"&$C10&"-"&TEXT(COUNTIFS($A$2:$A10,$A10,$C$2:$C10,$C10),"000") -> F1-AIINDEX-009 | E10: AIINDEX_ai-index-2025-ch3-responsible-ai.pdf | F10: F1_IA_y_Capacidades_Estrategicas/AI_Index_Stanford/recursos/AI_Index_Report/pdfs | G10: PDF
A11: F1 | B11: AI_Index_Stanford | C11: =VLOOKUP(B11,Indice!$B$1:$C$22,2,0) -> AIINDEX | D11: =$A11&"-"&$C11&"-"&TEXT(COUNTIFS($A$2:$A11,$A11,$C$2:$C11,$C11),"000") -> F1-AIINDEX-010 | E11: AIINDEX_ai-index-2025-ch4-economy.pdf | F11: F1_IA_y_Capacidades_Estrategicas/AI_Index_Stanford/recursos/AI_Index_Report/pdfs | G11: PDF
A12: F1 | B12: AI_Index_Stanford | C12: =VLOOKUP(B12,Indice!$B$1:$C$22,2,0) -> AIINDEX | D12: =$A12&"-"&$C12&"-"&TEXT(COUNTIFS($A$2:$A12,$A12,$C$2:$C12,$C12),"000") -> F1-AIINDEX-011 | E12: AIINDEX_ai-index-2025-ch5-science.pdf | F12: F1_IA_y_Capacidades_Estrategicas/AI_Index_Stanford/recursos/AI_Index_Report/pdfs | G12: PDF
A13: F1 | B13: AI_Index_Stanford | C13: =VLOOKUP(B13,Indice!$B$1:$C$22,2,0) -> AIINDEX | D13: =$A13&"-"&$C13&"-"&TEXT(COUNTIFS($A$2:$A13,$A13,$C$2:$C13,$C13),"000") -> F1-AIINDEX-012 | E13: AIINDEX_ai-index-2025-ch6-education.pdf | F13: F1_IA_y_Capacidades_Estrategicas/AI_Index_Stanford/recursos/AI_Index_Report/pdfs | G13: PDF
... A1827: F3 | B1827: SIPRI | C1827: =VLOOKUP(B1827,Indice!$B$1:$C$22,2,0) -> SIPRI | D1827: =$A1827&"-"&$C1827&"-"&TEXT(COUNTIFS($A$2:$A1827,$A1827,$C$2:$C1827,$C1827),"000") -> F3-SIPRI-128 | E1827: SIPRI_wps-sipri-nupi-fact-sheet.pdf | F1827: F3_Dinamicas_Territoriales/SIPRI/pdfs_full/2025 | G1827: PDF
